{
    "$schema": "../gen/schemas/desktop-schema.json",
    "identifier": "default",
    "description": "Capability for the main window",
    "windows": ["main"],
    "permissions": [
        "core:default",
        "opener:default",
        "dialog:default",
        "clipboard-manager:allow-read-text",
        "clipboard-manager:allow-write-text",
        "window-state:default",
        "autostart:allow-enable",
        "autostart:allow-disable",
        "autostart:allow-is-enabled",
        "global-shortcut:allow-register",
        "global-shortcut:allow-unregister",
        "global-shortcut:allow-is-registered",
        "global-shortcut:allow-unregister-all",
        "upload:default",
        "upload:allow-download",
        "http:default",
        "fs:default",
        "fs:allow-write-text-file",
        "fs:allow-read-text-file",
        "fs:allow-mkdir",
        "fs:allow-exists",
        "fs:allow-read-dir",
        "fs:allow-remove",
        "fs:allow-appdata-read",
        "fs:allow-appdata-write",
        "fs:allow-appdata-write-recursive",
        "fs:allow-applog-write",
        "fs:allow-applog-write-recursive",
        "os:default",
        "os:allow-hostname",
        "os:allow-platform",
        "os:allow-arch",
        "os:allow-version",
        "os:allow-family",
        "os:allow-locale",
        "http:allow-fetch",
        "http:allow-fetch-send"
    ]
}
